wzj/__init__.py
wzj/wp.py
wzj-1.0.dist-info/LICENSE
wzj-1.0.dist-info/METADATA
wzj-1.0.dist-info/WHEEL
wzj-1.0.dist-info/top_level.txt
wzj-1.0.dist-info/RECORD
